cpu_heater/__init__.py
cpu_heater/parallel.py
cpu_heater-0.1.0.dist-info/LICENSE
cpu_heater-0.1.0.dist-info/METADATA
cpu_heater-0.1.0.dist-info/WHEEL
cpu_heater-0.1.0.dist-info/top_level.txt
cpu_heater-0.1.0.dist-info/RECORD
